resotoeventlog/__init__.py
resotoeventlog/__main__.py
resotoeventlog/model.py
resotoeventlog/logs/__init__.py
resotoeventlog/logs/log_handler.py
resotoeventlog/ui/index.html
resotoeventlog/web/__init__.py
resotoeventlog/web/api.py
resotoeventlog/web/directives.py
resotoeventlog-3.4.2.dist-info/METADATA
resotoeventlog-3.4.2.dist-info/WHEEL
resotoeventlog-3.4.2.dist-info/entry_points.txt
resotoeventlog-3.4.2.dist-info/top_level.txt
resotoeventlog-3.4.2.dist-info/RECORD
