Metadata-Version: 2.1
Name: resotoeventlog
Version: 3.4.2
Summary: Event log aggregator for resoto.
Home-page: https://github.com/someengineering/resoto/tree/main/resotoeventlog
License: Apache Software License 2.0
Classifier: Programming Language :: Python :: 3
Requires-Python: >=3.5
Requires-Dist: aiohttp-swagger3 (==0.7.4)
Requires-Dist: aiohttp[speedups] (==3.8.4)
Requires-Dist: aiostream (==0.4.5)
Requires-Dist: resotolib (==3.4.2)
Requires-Dist: jsons (~=1.6.2)
